dbbasic_pipe/__init__.py
dbbasic_pipe/cli.py
dbbasic_pipe/coordinator.py
dbbasic_pipe/pcat.py
dbbasic_pipe/pfilter.py
dbbasic_pipe/plimit.py
dbbasic_pipe-0.1.0.dist-info/licenses/LICENSE
dbbasic_pipe-0.1.0.dist-info/METADATA
dbbasic_pipe-0.1.0.dist-info/WHEEL
dbbasic_pipe-0.1.0.dist-info/entry_points.txt
dbbasic_pipe-0.1.0.dist-info/top_level.txt
dbbasic_pipe-0.1.0.dist-info/RECORD
