Metadata-Version: 2.4
Name: dbbasic-pipe
Version: 0.1.0
Summary: SQL-style query optimization for Unix pipes with bidirectional flow control
Author-email: Dan Quellhorst <dan@quellhorst.com>
License: MIT
Project-URL: Homepage, https://github.com/askrobots/dbbasic-pipe
Project-URL: Repository, https://github.com/askrobots/dbbasic-pipe
Project-URL: Issues, https://github.com/askrobots/dbbasic-pipe/issues
Keywords: pipe,unix,pipeline,backpressure,streaming,sql,query
Classifier: Development Status :: 4 - Beta
Classifier: Intended Audience :: Developers
Classifier: License :: OSI Approved :: MIT License
Classifier: Programming Language :: Python :: 3
Classifier: Programming Language :: Python :: 3.8
Classifier: Programming Language :: Python :: 3.9
Classifier: Programming Language :: Python :: 3.10
Classifier: Programming Language :: Python :: 3.11
Classifier: Programming Language :: Python :: 3.12
Classifier: Topic :: System :: Shells
Classifier: Topic :: Utilities
Classifier: Operating System :: POSIX
Classifier: Operating System :: Unix
Classifier: Operating System :: MacOS
Requires-Python: >=3.8
License-File: LICENSE
Dynamic: license-file
